pretalx_friendlycaptcha/__init__.py
pretalx_friendlycaptcha/apps.py
pretalx_friendlycaptcha/forms.py
pretalx_friendlycaptcha/models.py
pretalx_friendlycaptcha/signals.py
pretalx_friendlycaptcha/urls.py
pretalx_friendlycaptcha/views.py
pretalx_friendlycaptcha/locale/.gitkeep
pretalx_friendlycaptcha/locale/django.pot
pretalx_friendlycaptcha/locale/ar/LC_MESSAGES/django.mo
pretalx_friendlycaptcha/locale/ar/LC_MESSAGES/django.po
pretalx_friendlycaptcha/locale/bg/LC_MESSAGES/django.mo
pretalx_friendlycaptcha/locale/bg/LC_MESSAGES/django.po
pretalx_friendlycaptcha/locale/ca/LC_MESSAGES/django.mo
pretalx_friendlycaptcha/locale/ca/LC_MESSAGES/django.po
pretalx_friendlycaptcha/locale/cs/LC_MESSAGES/django.mo
pretalx_friendlycaptcha/locale/cs/LC_MESSAGES/django.po
pretalx_friendlycaptcha/locale/de_DE/LC_MESSAGES/django.mo
pretalx_friendlycaptcha/locale/de_DE/LC_MESSAGES/django.po
pretalx_friendlycaptcha/locale/de_Formal/LC_MESSAGES/django.mo
pretalx_friendlycaptcha/locale/de_Formal/LC_MESSAGES/django.po
pretalx_friendlycaptcha/locale/el/LC_MESSAGES/django.mo
pretalx_friendlycaptcha/locale/el/LC_MESSAGES/django.po
pretalx_friendlycaptcha/locale/en_Mozilla/LC_MESSAGES/django.mo
pretalx_friendlycaptcha/locale/en_Mozilla/LC_MESSAGES/django.po
pretalx_friendlycaptcha/locale/es/LC_MESSAGES/django.mo
pretalx_friendlycaptcha/locale/es/LC_MESSAGES/django.po
pretalx_friendlycaptcha/locale/es_MX/LC_MESSAGES/django.mo
pretalx_friendlycaptcha/locale/es_MX/LC_MESSAGES/django.po
pretalx_friendlycaptcha/locale/fr_FR/LC_MESSAGES/django.mo
pretalx_friendlycaptcha/locale/fr_FR/LC_MESSAGES/django.po
pretalx_friendlycaptcha/locale/id/LC_MESSAGES/django.mo
pretalx_friendlycaptcha/locale/id/LC_MESSAGES/django.po
pretalx_friendlycaptcha/locale/it/LC_MESSAGES/django.mo
pretalx_friendlycaptcha/locale/it/LC_MESSAGES/django.po
pretalx_friendlycaptcha/locale/ja_JP/LC_MESSAGES/django.mo
pretalx_friendlycaptcha/locale/ja_JP/LC_MESSAGES/django.po
pretalx_friendlycaptcha/locale/ko/LC_MESSAGES/django.mo
pretalx_friendlycaptcha-0.2.1.dist-info/licenses/LICENSE
pretalx_friendlycaptcha-0.2.1.dist-info/METADATA
pretalx_friendlycaptcha-0.2.1.dist-info/WHEEL
pretalx_friendlycaptcha-0.2.1.dist-info/entry_points.txt
pretalx_friendlycaptcha-0.2.1.dist-info/top_level.txt
pretalx_friendlycaptcha-0.2.1.dist-info/RECORD
