Metadata-Version: 2.4
Name: pretalx-friendlycaptcha
Version: 0.2.1
Summary: Adds a new, final CfP step with the FriendlyCaptcha captcha, in order to reduce spam.
Author-email: Tobias Kunze <r@rixx.de>
Maintainer-email: Tobias Kunze <r@rixx.de>
License: Apache Software License
Project-URL: homepage, https://github.com/pretalx/pretalx-friendlycaptcha
Project-URL: repository, https://github.com/pretalx/pretalx-friendlycaptcha.git
Keywords: pretalx
License-File: LICENSE
Dynamic: license-file
